dolma-1.2.1.dist-info/METADATA
dolma-1.2.1.dist-info/WHEEL
dolma-1.2.1.dist-info/entry_points.txt
dolma-1.2.1.dist-info/licenses/LICENSE
dolma/__init__.py
dolma/cli/__init__.py
dolma/cli/__main__.py
dolma/cli/analyzer.py
dolma/cli/deduper.py
dolma/cli/main.py
dolma/cli/mixer.py
dolma/cli/resolvers.py
dolma/cli/shared.py
dolma/cli/tagger.py
dolma/cli/tokenizer.py
dolma/cli/warc.py
dolma/core/__init__.py
dolma/core/analyzer.py
dolma/core/binning.py
dolma/core/data_types.py
dolma/core/errors.py
dolma/core/ft_dataset.py
dolma/core/ft_tagger.py
dolma/core/loggers.py
dolma/core/parallel.py
dolma/core/paths.py
dolma/core/registry.py
dolma/core/runtime.py
dolma/core/taggers.py
dolma/core/trainer.py
dolma/core/url_blocker.py
dolma/core/utils.py
dolma/core/vizualizer.py
dolma/data/ext_to_lang_mapping.json
dolma/data/naughty_words_en.txt
dolma/dolma.cpython-311-aarch64-linux-gnu.so
dolma/py.typed
dolma/taggers/__init__.py
dolma/taggers/c4.py
dolma/taggers/code/__init__.py
dolma/taggers/code/code_taggers.py
dolma/taggers/code/starcoder.py
dolma/taggers/code/utils.py
dolma/taggers/code_composition.py
dolma/taggers/gopher.py
dolma/taggers/jigsaw.py
dolma/taggers/language.py
dolma/taggers/length.py
dolma/taggers/licenses.py
dolma/taggers/pii.py
dolma/taggers/punctuation.py
dolma/taggers/quality.py
dolma/taggers/repetitions/__init__.py
dolma/taggers/repetitions/repetitions_taggers.py
dolma/taggers/repetitions/utils.py
dolma/taggers/sampling.py
dolma/taggers/tokenizers.py
dolma/taggers/url.py
dolma/tokenizer/__init__.py
dolma/tokenizer/data_types.py
dolma/tokenizer/executor.py
dolma/tokenizer/memmap_writer.py
dolma/tokenizer/reshard.py
dolma/tokenizer/tokenizer.py
dolma/warc/__init__.py
dolma/warc/linearizers.py
dolma/warc/processor.py
dolma/warc/record_info.py
dolma/warc/utils.py
dolma-1.2.1.dist-info/RECORD
