Metadata-Version: 2.4
Name: dolma
Version: 1.2.1
Classifier: Development Status :: 5 - Production/Stable
Classifier: Intended Audience :: Science/Research
Classifier: License :: OSI Approved :: Apache Software License
Classifier: Programming Language :: Python :: Implementation :: CPython
Classifier: Programming Language :: Rust
Classifier: Topic :: Scientific/Engineering :: Artificial Intelligence
Classifier: Topic :: Text Processing
Classifier: Typing :: Typed
Requires-Dist: anyascii>=0.3.2
Requires-Dist: blingfire==0.1.8
Requires-Dist: boto3
Requires-Dist: fasttext-wheel==0.9.2
Requires-Dist: fsspec>=2023.6.0
Requires-Dist: jsonpath-ng
Requires-Dist: jq
Requires-Dist: msgspec>=0.14.2
Requires-Dist: nltk>=3.9.1
Requires-Dist: omegaconf>=2.3.0
Requires-Dist: platformdirs>=4.2.0
Requires-Dist: pyyaml
Requires-Dist: python-dotenv>=0.19.0
Requires-Dist: requests
Requires-Dist: rich
Requires-Dist: s3fs==2023.6.0
Requires-Dist: smart-open>=7.0.4
Requires-Dist: tokenizers>=0.15.0,<=0.19.1
Requires-Dist: tqdm
Requires-Dist: uniseg
Requires-Dist: numpy<2
Requires-Dist: necessary>=0.4.3
Requires-Dist: charset-normalizer>=3.2.0
Requires-Dist: zstandard>=0.23.0
Requires-Dist: flake8-pyproject>=1.1.0 ; extra == 'dev'
Requires-Dist: black>=22.6.0 ; extra == 'dev'
Requires-Dist: flake8-pyi>=22.8.1 ; extra == 'dev'
Requires-Dist: flake8>=5.0 ; extra == 'dev'
Requires-Dist: ipdb>=0.13.0 ; extra == 'dev'
Requires-Dist: ipython>=8.4.0 ; extra == 'dev'
Requires-Dist: isort>=5.10.1 ; extra == 'dev'
Requires-Dist: mypy==0.971 ; extra == 'dev'
Requires-Dist: pytest>=5.2 ; extra == 'dev'
Requires-Dist: types-pyyaml ; extra == 'dev'
Requires-Dist: types-dateparser ; extra == 'dev'
Requires-Dist: detect-secrets==1.4.0 ; extra == 'code'
Requires-Dist: beautifulsoup4>=4 ; extra == 'code'
Requires-Dist: pygments ; extra == 'code'
Requires-Dist: regex ; extra == 'code'
Requires-Dist: regex ; extra == 'pii'
Requires-Dist: fasttext-wheel==0.9.2 ; extra == 'lang'
Requires-Dist: pycld2 ; extra == 'lang'
Requires-Dist: lingua-language-detector>=2.0.0 ; extra == 'lang'
Requires-Dist: fastwarc ; extra == 'warc'
Requires-Dist: w3lib ; extra == 'warc'
Requires-Dist: url-normalize ; extra == 'warc'
Requires-Dist: dolma[warc] ; extra == 'trafilatura'
Requires-Dist: trafilatura>=1.6.1 ; extra == 'trafilatura'
Requires-Dist: brotli ; extra == 'trafilatura'
Requires-Dist: cchardet>=2.1.7 ; python_full_version < '3.11' and extra == 'trafilatura'
Requires-Dist: faust-cchardet>=2.1.18 ; python_full_version >= '3.11' and extra == 'trafilatura'
Requires-Dist: htmldate[speed]>=1.4.3 ; extra == 'trafilatura'
Requires-Dist: py3langid>=0.2.2 ; extra == 'trafilatura'
Requires-Dist: dolma[warc] ; extra == 'resiliparse'
Requires-Dist: resiliparse ; extra == 'resiliparse'
Requires-Dist: dolma[dev] ; extra == 'all'
Requires-Dist: dolma[code] ; extra == 'all'
Requires-Dist: dolma[pii] ; extra == 'all'
Requires-Dist: dolma[trafilatura] ; extra == 'all'
Requires-Dist: dolma[resiliparse] ; extra == 'all'
Requires-Dist: dolma[lang] ; extra == 'all'
Provides-Extra: dev
Provides-Extra: code
Provides-Extra: pii
Provides-Extra: lang
Provides-Extra: warc
Provides-Extra: trafilatura
Provides-Extra: resiliparse
Provides-Extra: all
License-File: LICENSE
Summary: Toolkit for pre-processing LLM training data.
Author-email: Allen Institute for Artificial Intelligence <contact@allenai.org>, Luca Soldaini <luca@soldaini.net>, Kyle Lo <kylel@allenai.org>, Rodney Kinney <rodneyk@allenai.org>, Aakanksha Naik <aakankshan@allenai.org>, Abhilasha Ravichander <abhilashar@allenai.org>, Akshita Bhagia <akshitab@allenai.org>, Dirk Groeneveld <dirkg@allenai.org>, Dustin Schwenk <dustins@allenai.org>, Ian Magnusson <ianm@allenai.org>, Khyathi Chandu <khyathic@allenai.org>
Maintainer-email: Allen Institute for Artificial Intelligence <contact@allenai.org>
License: Apache-2.0
Requires-Python: >=3.10, <3.13
Project-URL: Homepage, https://github.com/allenai/dolma
